piemmer/__init__.py
piemmer/bake.py
piemmer/harvest.py
piemmer/tests.py
piemmer/data/test_case_1.csv
piemmer/data/test_case_3.csv
piemmer/data/bake_data_dir_4/information_rich_features_summary.csv
piemmer/data/bake_data_dir_4/filtered_data/group_A__filterd_data.csv
piemmer/data/bake_data_dir_4/filtered_data/group_B__filterd_data.csv
piemmer/data/bake_data_dir_5/another_information_rich_features_summary.csv
piemmer/data/bake_data_dir_5/information_rich_features_summary.csv
piemmer/data/bake_data_dir_6/_retrospect_permanova_parameter.csv
piemmer/data/bake_data_dir_6/filtered_infoRich__PCA_coordinates.csv
piemmer/data/bake_data_dir_7/_retrospect_individaul_coloring_parameter.csv
piemmer/data/bake_data_dir_8/case1.csv
piemmer/data/bake_data_dir_8/case2.csv
piemmer/data/bake_data_dir_8/case2_in_folder/case2__1.csv
piemmer/data/bake_data_dir_8/case2_in_folder/case2__2.csv
piemmer/data/bake_data_dir_8/case3_in_folder/case3__1.csv
piemmer/data/bake_data_dir_8/case3_in_folder/case3__2.csv
piemmer/data/bake_data_dir_9/filtered_infoRich__PCA_coordinates.csv
piemmer/data/bake_data_dir_9/filtered_infoRich__data_colmean.csv
piemmer/data/bake_data_dir_9/filtered_infoRich__data_colstd.csv
piemmer/data/bake_data_dir_9/filtered_infoRich__transformation_matrix.csv
piemmer/data/bake_data_dir_9/incorrect__data_colstd.csv
piemmer/data/bake_data_dir_9/incorrect_colmean_1.csv
piemmer/data/bake_data_dir_9/incorrect_colmean_2.csv
piemmer/data/bake_data_dir_9/new_obs_case1.csv
piemmer/data/bake_data_dir_9/new_observation.csv
piemmer/data/bake_data_dir_9/multiple_input_file/new_obs_case1.csv
piemmer/data/bake_data_dir_9/multiple_input_file/new_obs_case2.csv
piemmer/data/bake_data_dir_9/s1_s2/filtered_infoRich__PCA_coordinates.csv
piemmer/data/bake_data_dir_9/s1_s2/filtered_infoRich__data_colmean.csv
piemmer/data/bake_data_dir_9/s1_s2/filtered_infoRich__data_colstd.csv
piemmer/data/bake_data_dir_9/s1_s2/filtered_infoRich__transformation_matrix.csv
piemmer-1.0.5.dist-info/METADATA
piemmer-1.0.5.dist-info/WHEEL
piemmer-1.0.5.dist-info/top_level.txt
piemmer-1.0.5.dist-info/RECORD
